{
  "display": {
    "icon": {
      "item": "speedrunnermod:igneous_rock"
    },
    "title": "Hard Rock",
    "description": "Obtain an Igneous Rock",
    "frame": "task",
    "show_toast": true,
    "announce_to_chat": true,
    "hidden": false
  },
  "parent": "minecraft:story/upgrade_tools",
  "criteria": {
    "has_igneous_rock": {
      "trigger": "minecraft:inventory_changed",
      "conditions": {
        "items": [
          {
            "items": [
              "speedrunnermod:igneous_rock"
            ]
          }
        ]
      }
    }
  },
  "requirements": [
    [
      "has_igneous_rock"
    ]
  ]
}