{
  "parent": "minecraft:recipes/root",
  "criteria": {
    "has_speedrunner_block": {
      "trigger": "minecraft:inventory_changed",
      "conditions": {
        "items": [
          {
            "items": [
              "speedrunnermod:speedrunner_block"
            ]
          }
        ]
      }
    },
    "has_the_recipe": {
      "trigger": "minecraft:recipe_unlocked",
      "conditions": {
        "recipe": "minecraft:anvil_from_speedrunner_block_and_ingot"
      }
    }
  },
  "requirements": [
    [
      "has_speedrunner_block",
      "has_the_recipe"
    ]
  ],
  "rewards": {
    "recipes": [
      "minecraft:anvil_from_speedrunner_block_and_ingot"
    ]
  }
}
